{"time_str": "07:03 AM", "date_str": "Aug 03, 2026", "city_metrics": ["Tiles: 1344", "Road coverage: 740 (55.1%)", "Water: 31 (2.3%)", "Parks: 76 (5.7%)", "Residential: 174 (12.9%)", "Commercial: 130 (9.7%)", "Offices: 84 (6.2%)", "Industrial: 109 (8.1%)"], "population_metrics": ["Citizens: 16", "Households: 5", "Employed: 8 (50.0%)", "Unemployed: 1 (6.2%)", "Students: 7 (43.8%)", "Retired: 0 (0.0%)", "Active commuters: 0", "Simulation: running"], "citizens": [{"id": 1, "name": "Maya Patel", "gender": "female", "age_group": "adult", "employment": "employed", "profession": "office", "address": "E-000", "stage": "home"}, {"id": 2, "name": "Arjun Patel", "gender": "male", "age_group": "adult", "employment": "employed", "profession": "industrial", "address": "E-000", "stage": "work"}, {"id": 3, "name": "Leah Garcia", "gender": "female", "age_group": "adult", "employment": "employed", "profession": "retail", "address": "C-000", "stage": "home"}, {"id": 4, "name": "Naomi Reed", "gender": "female", "age_group": "adult", "employment": "employed", "profession": "service", "address": "C-000", "stage": "home"}, {"id": 5, "name": "Mateo Garcia", "gender": "male", "age_group": "teen", "employment": "student", "profession": "student", "address": "C-000", "stage": "home"}, {"id": 6, "name": "Victor Huang", "gender": "male", "age_group": "adult", "employment": "employed", "profession": "office", "address": "A-000", "stage": "home"}, {"id": 7, "name": "Elena Huang", "gender": "female", "age_group": "adult", "employment": "employed", "profession": "service", "address": "A-000", "stage": "home"}, {"id": 8, "name": "Carlos Mendes", "gender": "male", "age_group": "adult", "employment": "employed", "profession": "industrial", "address": "A-001", "stage": "work"}, {"id": 9, "name": "Sofia Mendes", "gender": "female", "age_group": "adult", "employment": "employed", "profession": "retail", "address": "A-001", "stage": "home"}, {"id": 10, "name": "Elias Stone", "gender": "male", "age_group": "adult", "employment": "unemployed", "profession": "none", "address": "F-000", "stage": "home"}, {"id": 11, "name": "Nika Patel", "gender": "female", "age_group": "child", "employment": "student", "profession": "student", "address": "E-000", "stage": "home"}, {"id": 12, "name": "Nika Patel", "gender": "female", "age_group": "child", "employment": "student", "profession": "student", "address": "A-000", "stage": "home"}, {"id": 13, "name": "Nika Patel", "gender": "female", "age_group": "child", "employment": "student", "profession": "student", "address": "A-001", "stage": "home"}, {"id": 14, "name": "Nika Patel", "gender": "female", "age_group": "child", "employment": "student", "profession": "student", "address": "E-000", "stage": "home"}, {"id": 15, "name": "Nika Patel", "gender": "female", "age_group": "child", "employment": "student", "profession": "student", "address": "A-000", "stage": "home"}, {"id": 16, "name": "Nika Patel", "gender": "female", "age_group": "child", "employment": "student", "profession": "student", "address": "A-001", "stage": "home"}], "events": ["2026-05-31: Nika Patel was born at E-000.", "2026-05-31: Nika Patel was born at A-000.", "2026-05-31: Nika Patel was born at A-001.", "2026-07-20: A fire broke out in a building.", "2026-07-24: An accident happened on the streets.", "2026-07-30: A fair is being held in the city.", "Conversation: Elena Huang speaking to Victor Huang", "Conversation: Nika Patel speaking to ", "Conversation: Mateo Garcia speaking to Naomi Reed"]}